flask_wkhtmltopdf.py
Flask_WkHTMLtoPDF_tmsl-0.1.2.dist-info/LICENSE.txt
Flask_WkHTMLtoPDF_tmsl-0.1.2.dist-info/METADATA
Flask_WkHTMLtoPDF_tmsl-0.1.2.dist-info/WHEEL
Flask_WkHTMLtoPDF_tmsl-0.1.2.dist-info/top_level.txt
Flask_WkHTMLtoPDF_tmsl-0.1.2.dist-info/RECORD
