Metadata-Version: 2.1
Name: Flask-WkHTMLtoPDF-tmsl
Version: 0.1.2
Summary: Convert JavaScript dependent Flask templates into PDFs with wkhtmltopdf.
Author-email: Chris Griffin <cwg23@georgetown.edu>
License: The MIT License (MIT)        
Project-URL: Homepage, https://github.com/thinkmorestupidless/flask-wkhtmltopdf
Project-URL: Bug Tracker, https://github.com/thinkmorestupidless/flask-wkhtmltopdf/issues
Classifier: Development Status :: 3 - Alpha
Classifier: Environment :: Web Environment
Classifier: Framework :: Flask
Classifier: Intended Audience :: Developers
Classifier: License :: OSI Approved :: MIT License
Classifier: Operating System :: OS Independent
Classifier: Programming Language :: Python
Classifier: Topic :: Internet :: WWW/HTTP :: Dynamic Content
Classifier: Topic :: Software Development :: Libraries :: Python Modules
Classifier: Topic :: Printing
Requires-Python: >=3.7
License-File: LICENSE.txt
Requires-Dist: Flask
Requires-Dist: Celery
